{
	"mapId" : 1721978946014,
	"mapName" : "MAP_21floor_1721978829",
	"stations" : 
	[
		{
			"stationId" : 1721979032608,
			"stationName" : "start",
			"x" : "7.22794",
			"y" : "-3.15009",
			"yaw" : "-0.73772"
		},
		{
			"stationId" : 1721979050809,
			"stationName" : "temp",
			"x" : "9.27412",
			"y" : "-6.82995",
			"yaw" : "-0.58739"
		},
		{
			"stationId" : 1722220729312,
			"stationName" : "111",
			"x" : "10.65895",
			"y" : "-1.94334",
			"yaw" : "-2.17129"
		},
		{
			"stationId" : 1722220830469,
			"stationName" : "222",
			"x" : "7.84748",
			"y" : "-6.36913",
			"yaw" : "0.94484"
		}
	]
}
